README.rst
setup.py
appsettings/__init__.py
appsettings/parser.py
appsettings/test_parser.py
appsettings.egg-info/PKG-INFO
appsettings.egg-info/SOURCES.txt
appsettings.egg-info/dependency_links.txt
appsettings.egg-info/not-zip-safe
appsettings.egg-info/requires.txt
appsettings.egg-info/top_level.txt