Metadata-Version: 1.0
Name: appsettings
Version: 0.3.1
Summary: Argparse wrapper that supports fallback settings in env vars and/or a yaml file.
Home-page: http://bits.btubbs.com/appsettings/
Author: Brent Tubbs
Author-email: brent.tubbs@gmail.com
License: UNKNOWN
Platform: UNKNOWN
